trafficlight_controllers.v


module traffic_light_controllers(
    input clk,rst,
    output reg [2:0]light_M1,
    output reg [2:0]light_M2,
    output reg [2:0]light_MT,
    output reg [2:0]light_S
);

parameter s1=0,s2=1,s3=2,s4=3,s5=4,s6=5;
reg [3:0]count;
reg[2:0]ps;
parameter TMG=7,TY=2,TTG=5,TSG=3;

always@(posedge clk or posedge rst)
begin
    if(rst==1)
    begin
        ps<=s1;
        count<=0;
    end
    else
    begin

    case(ps)
    s1:if(count<TMG)
    begin
    ps<=s1;
    count<=count+1;
    end
    else
    begin
        ps<=s2;
        count<=0;
    end
    s2:if(count<TY)
    begin
    ps<=s2;
    count<=count+1;
    end
    else
    begin
        ps<=s3;
        count<=0;
    end
    s3:if(count<TTG)
    begin
    ps<=s3;
    count<=count+1;
    end
    else
    begin
        ps<=s4;
        count<=0;
    end
    s4:if(count<TY)
    begin
    ps<=s4;
    count<=count+1;
    end
    else
    begin
        ps<=s5;
        count<=0;
    end
    s5:if(count<TSG)
    begin
    ps<=s5;
    count<=count+1;
    end
    else
    begin
        ps<=s6;
        count<=0;
    end
    s6:if(count<TY)
    begin
    ps<=s6;
    count<=count+1;
    end
    else
    begin
        ps<=s1;
        count<=0;
    end
    default: ps<=s1;
    endcase
    end

end

always@(ps)
begin

    case(ps)

    s1:
    begin
        light_M1<=3'b001;
        light_M2<=3'b001;
        light_MT<=3'b100;
        light_S<=3'b100;
    end

     s2:
    begin
        light_M1<=3'b001;
        light_M2<=3'b010;
        light_MT<=3'b100;
        light_S<=3'b100;
    end
      s3:
    begin
        light_M1<=3'b001;
        light_M2<=3'b100;
        light_MT<=3'b001;
        light_S<=3'b100;
    end
      s4:
    begin
        light_M1<=3'b010;
        light_M2<=3'b100;
        light_MT<=3'b010;
        light_S<=3'b100;
    end
      s5:
    begin
        light_M1<=3'b100;
        light_M2<=3'b100;
        light_MT<=3'b100;
        light_S<=3'b010;
    end
      s6:
    begin
        light_M1<=3'b100;
        light_M2<=3'b100;
        light_MT<=3'b100;
        light_S<=3'b001;
    end

    endcase
end  
endmodule

trafficlight_controllers_tb.v


module traffic_light_controllers_tb;
reg clk,rst;
wire [2:0]light_M1;
wire [2:0]light_M2;
wire [2:0]light_MT;
wire [2:0]light_S;

traffic_light_controllers dut(
    .clk(clk),
    .rst(rst),
    .light_M1(light_M1),
    .light_M2(light_M2),
    .light_MT(light_MT),
    .light_S(light_S)
    );

    initial 
    begin
        clk=1'b0;
        forever #5 clk=~clk;

    end
    initial
    begin
        
   $dumpfile("trafficlight_controllers.vcd");
    $dumpvars(0,traffic_light_controllers_tb);

    rst = 1;
    #20;
    rst = 0;

 #500;
    $finish;
    end
    
    
endmodule

trafficlight_controllers.vcd
$date
	Sun Mar 15 15:04:49 2026
$end
$version
	Icarus Verilog
$end
$timescale
	1s
$end
$scope module traffic_light_controllers_tb $end
$var wire 3 ! light_S [2:0] $end
$var wire 3 " light_MT [2:0] $end
$var wire 3 # light_M2 [2:0] $end
$var wire 3 $ light_M1 [2:0] $end
$var reg 1 % clk $end
$var reg 1 & rst $end
$scope module dut $end
$var wire 1 % clk $end
$var wire 1 & rst $end
$var reg 4 ' count [3:0] $end
$var reg 3 ( light_M1 [2:0] $end
$var reg 3 ) light_M2 [2:0] $end
$var reg 3 * light_MT [2:0] $end
$var reg 3 + light_S [2:0] $end
$var reg 3 , ps [2:0] $end
$upscope $end
$upscope $end
$enddefinitions $end
#0
$dumpvars
b0 ,
b100 +
b100 *
b1 )
b1 (
b0 '
1&
0%
b1 $
b1 #
b100 "
b100 !
$end
#5
1%
#10
0%
#15
1%
#20
0%
0&
#25
b1 '
1%
#30
0%
#35
b10 '
1%
#40
0%
#45
b11 '
1%
#50
0%
#55
b100 '
1%
#60
0%
#65
b101 '
1%
#70
0%
#75
b110 '
1%
#80
0%
#85
b111 '
1%
#90
0%
#95
b10 #
b10 )
b0 '
b1 ,
1%
#100
0%
#105
b1 '
1%
#110
0%
#115
b10 '
1%
#120
0%
#125
b1 "
b1 *
b100 #
b100 )
b0 '
b10 ,
1%
#130
0%
#135
b1 '
1%
#140
0%
#145
b10 '
1%
#150
0%
#155
b11 '
1%
#160
0%
#165
b100 '
1%
#170
0%
#175
b101 '
1%
#180
0%
#185
b10 "
b10 *
b10 $
b10 (
b0 '
b11 ,
1%
#190
0%
#195
b1 '
1%
#200
0%
#205
b10 '
1%
#210
0%
#215
b10 !
b10 +
b100 "
b100 *
b100 $
b100 (
b0 '
b100 ,
1%
#220
0%
#225
b1 '
1%
#230
0%
#235
b10 '
1%
#240
0%
#245
b11 '
1%
#250
0%
#255
b1 !
b1 +
b0 '
b101 ,
1%
#260
0%
#265
b1 '
1%
#270
0%
#275
b10 '
1%
#280
0%
#285
b100 !
b100 +
b1 #
b1 )
b1 $
b1 (
b0 '
b0 ,
1%
#290
0%
#295
b1 '
1%
#300
0%
#305
b10 '
1%
#310
0%
#315
b11 '
1%
#320
0%
#325
b100 '
1%
#330
0%
#335
b101 '
1%
#340
0%
#345
b110 '
1%
#350
0%
#355
b111 '
1%
#360
0%
#365
b10 #
b10 )
b0 '
b1 ,
1%
#370
0%
#375
b1 '
1%
#380
0%
#385
b10 '
1%
#390
0%
#395
b1 "
b1 *
b100 #
b100 )
b0 '
b10 ,
1%
#400
0%
#405
b1 '
1%
#410
0%
#415
b10 '
1%
#420
0%
#425
b11 '
1%
#430
0%
#435
b100 '
1%
#440
0%
#445
b101 '
1%
#450
0%
#455
b10 "
b10 *
b10 $
b10 (
b0 '
b11 ,
1%
#460
0%
#465
b1 '
1%
#470
0%
#475
b10 '
1%
#480
0%
#485
b10 !
b10 +
b100 "
b100 *
b100 $
b100 (
b0 '
b100 ,
1%
#490
0%
#495
b1 '
1%
#500
0%
#505
b10 '
1%
#510
0%
#515
b11 '
1%
